{
  "employees": [
    {
      "name": "Raghu",
      "agentId": "raghu_workspace",
      "tokensIn": 14307935,
      "tokensOut": 4013421,
      "totalTokens": 18321356,
      "weeklyTokensIn": 5075323,
      "weeklyTokensOut": 1423645,
      "weeklyTokens": 6498968,
      "estimatedHours": 29.7,
      "weeklyHours": 10.5,
      "totalCost": 42.484,
      "weeklyCost": 15.07,
      "adminCost": 0.0,
      "weeklyAdminCost": 0.0,
      "employeeCost": 42.484,
      "weeklyEmployeeCost": 15.07,
      "adminSessionCount": 0,
      "totalRuntimeMs": 781998,
      "weeklyRuntimeMs": 277391,
      "streak": 12,
      "lastActive": "1778791295260",
      "sessionCount": 108,
      "rank": 1
    },
    {
      "name": "Sagar",
      "agentId": "sagar_workspace",
      "tokensIn": 9989943,
      "tokensOut": 4163159,
      "totalTokens": 14153102,
      "weeklyTokensIn": 2967419,
      "weeklyTokensOut": 1236628,
      "weeklyTokens": 4204047,
      "estimatedHours": 21.9,
      "weeklyHours": 6.5,
      "totalCost": 35.6432,
      "weeklyCost": 10.5875,
      "adminCost": 0.0,
      "weeklyAdminCost": 0.0,
      "employeeCost": 35.6432,
      "weeklyEmployeeCost": 10.5875,
      "adminSessionCount": 0,
      "totalRuntimeMs": 743288,
      "weeklyRuntimeMs": 220786,
      "streak": 11,
      "lastActive": "1778918806989",
      "sessionCount": 99,
      "rank": 2
    },
    {
      "name": "Chris",
      "agentId": "chris_workspace",
      "tokensIn": 9557446,
      "tokensOut": 3602111,
      "totalTokens": 13159557,
      "weeklyTokensIn": 2961948,
      "weeklyTokensOut": 1116331,
      "weeklyTokens": 4078279,
      "estimatedHours": 23.8,
      "weeklyHours": 7.4,
      "totalCost": 30.3784,
      "weeklyCost": 9.4146,
      "adminCost": 0.0,
      "weeklyAdminCost": 0.0,
      "employeeCost": 30.3784,
      "weeklyEmployeeCost": 9.4146,
      "adminSessionCount": 0,
      "totalRuntimeMs": 344218,
      "weeklyRuntimeMs": 106676,
      "streak": 10,
      "lastActive": "1778858966572",
      "sessionCount": 81,
      "rank": 3
    },
    {
      "name": "Vignesh",
      "agentId": "vignesh_workspace",
      "tokensIn": 7540858,
      "tokensOut": 3126961,
      "totalTokens": 10667819,
      "weeklyTokensIn": 2380857,
      "weeklyTokensOut": 987268,
      "weeklyTokens": 3368125,
      "estimatedHours": 19.1,
      "weeklyHours": 6.0,
      "totalCost": 25.9418,
      "weeklyCost": 8.1905,
      "adminCost": 0.0,
      "weeklyAdminCost": 0.0,
      "employeeCost": 25.9418,
      "weeklyEmployeeCost": 8.1905,
      "adminSessionCount": 0,
      "totalRuntimeMs": 12072,
      "weeklyRuntimeMs": 3811,
      "streak": 9,
      "lastActive": "1778708203163",
      "sessionCount": 66,
      "rank": 4
    },
    {
      "name": "Rahul",
      "agentId": "rahul_workspace",
      "tokensIn": 7835327,
      "tokensOut": 2127389,
      "totalTokens": 9962716,
      "weeklyTokensIn": 1961364,
      "weeklyTokensOut": 532536,
      "weeklyTokens": 2493900,
      "estimatedHours": 16.8,
      "weeklyHours": 4.2,
      "totalCost": 24.5321,
      "weeklyCost": 6.141,
      "adminCost": 0.0,
      "weeklyAdminCost": 0.0,
      "employeeCost": 24.5321,
      "weeklyEmployeeCost": 6.141,
      "adminSessionCount": 0,
      "totalRuntimeMs": 601352,
      "weeklyRuntimeMs": 150532,
      "streak": 8,
      "lastActive": "1778789594951",
      "sessionCount": 70,
      "rank": 5
    },
    {
      "name": "Nav",
      "agentId": "nav_workspace",
      "tokensIn": 6883824,
      "tokensOut": 2165988,
      "totalTokens": 9049812,
      "weeklyTokensIn": 2500822,
      "weeklyTokensOut": 786882,
      "weeklyTokens": 3287704,
      "estimatedHours": 17.4,
      "weeklyHours": 6.3,
      "totalCost": 20.5266,
      "weeklyCost": 7.4571,
      "adminCost": 0.0,
      "weeklyAdminCost": 0.0,
      "employeeCost": 20.5266,
      "weeklyEmployeeCost": 7.4571,
      "adminSessionCount": 0,
      "totalRuntimeMs": 392782,
      "weeklyRuntimeMs": 142693,
      "streak": 7,
      "lastActive": "1778694598038",
      "sessionCount": 65,
      "rank": 6
    },
    {
      "name": "Omkar",
      "agentId": "omkar_workspace",
      "tokensIn": 5450045,
      "tokensOut": 2227786,
      "totalTokens": 7677831,
      "weeklyTokensIn": 2066934,
      "weeklyTokensOut": 844890,
      "weeklyTokens": 2911824,
      "estimatedHours": 13.6,
      "weeklyHours": 5.2,
      "totalCost": 18.6241,
      "weeklyCost": 7.0632,
      "adminCost": 0.0,
      "weeklyAdminCost": 0.0,
      "employeeCost": 18.6241,
      "weeklyEmployeeCost": 7.0632,
      "adminSessionCount": 0,
      "totalRuntimeMs": 14506,
      "weeklyRuntimeMs": 5501,
      "streak": 6,
      "lastActive": "1778866114784",
      "sessionCount": 49,
      "rank": 7
    },
    {
      "name": "Ashwin",
      "agentId": "ashwin_workspace",
      "tokensIn": 4423016,
      "tokensOut": 1354597,
      "totalTokens": 5777613,
      "weeklyTokensIn": 1410180,
      "weeklyTokensOut": 431883,
      "weeklyTokens": 1842063,
      "estimatedHours": 10.8,
      "weeklyHours": 3.4,
      "totalCost": 16.1291,
      "weeklyCost": 5.1424,
      "adminCost": 0.0,
      "weeklyAdminCost": 0.0,
      "employeeCost": 16.1291,
      "weeklyEmployeeCost": 5.1424,
      "adminSessionCount": 0,
      "totalRuntimeMs": 2238,
      "weeklyRuntimeMs": 713,
      "streak": 5,
      "lastActive": "1778772740864",
      "sessionCount": 39,
      "rank": 8
    },
    {
      "name": "Pooja",
      "agentId": "pooja_workspace",
      "tokensIn": 3672801,
      "tokensOut": 1275812,
      "totalTokens": 4948613,
      "weeklyTokensIn": 1426845,
      "weeklyTokensOut": 495640,
      "weeklyTokens": 1922485,
      "estimatedHours": 7.6,
      "weeklyHours": 3.0,
      "totalCost": 11.2565,
      "weeklyCost": 4.373,
      "adminCost": 0.0,
      "weeklyAdminCost": 0.0,
      "employeeCost": 11.2565,
      "weeklyEmployeeCost": 4.373,
      "adminSessionCount": 0,
      "totalRuntimeMs": 381706,
      "weeklyRuntimeMs": 148288,
      "streak": 4,
      "lastActive": "1778827863413",
      "sessionCount": 33,
      "rank": 9
    },
    {
      "name": "Dipak",
      "agentId": "dipak_workspace",
      "tokensIn": 2562194,
      "tokensOut": 963685,
      "totalTokens": 3525879,
      "weeklyTokensIn": 807641,
      "weeklyTokensOut": 303768,
      "weeklyTokens": 1111409,
      "estimatedHours": 5.5,
      "weeklyHours": 1.7,
      "totalCost": 9.3271,
      "weeklyCost": 2.94,
      "adminCost": 0.0,
      "weeklyAdminCost": 0.0,
      "employeeCost": 9.3271,
      "weeklyEmployeeCost": 2.94,
      "adminSessionCount": 0,
      "totalRuntimeMs": 30698,
      "weeklyRuntimeMs": 9676,
      "streak": 3,
      "lastActive": "1778754435578",
      "sessionCount": 28,
      "rank": 10
    },
    {
      "name": "Pramod",
      "agentId": "pramod_workspace",
      "tokensIn": 3108015,
      "tokensOut": 1013700,
      "totalTokens": 4121715,
      "weeklyTokensIn": 1128317,
      "weeklyTokensOut": 368009,
      "weeklyTokens": 1496326,
      "estimatedHours": 6.4,
      "weeklyHours": 2.3,
      "totalCost": 9.1958,
      "weeklyCost": 3.3384,
      "adminCost": 0.0,
      "weeklyAdminCost": 0.0,
      "employeeCost": 9.1958,
      "weeklyEmployeeCost": 3.3384,
      "adminSessionCount": 0,
      "totalRuntimeMs": 357062,
      "weeklyRuntimeMs": 129625,
      "streak": 3,
      "lastActive": "1778862721899",
      "sessionCount": 27,
      "rank": 11
    },
    {
      "name": "Jatin",
      "agentId": "jatin_workspace",
      "tokensIn": 2217559,
      "tokensOut": 789744,
      "totalTokens": 3007303,
      "weeklyTokensIn": 861222,
      "weeklyTokensOut": 306709,
      "weeklyTokens": 1167931,
      "estimatedHours": 5.5,
      "weeklyHours": 2.1,
      "totalCost": 8.0123,
      "weeklyCost": 3.1117,
      "adminCost": 0.0,
      "weeklyAdminCost": 0.0,
      "employeeCost": 8.0123,
      "weeklyEmployeeCost": 3.1117,
      "adminSessionCount": 0,
      "totalRuntimeMs": 79413,
      "weeklyRuntimeMs": 30841,
      "streak": 2,
      "lastActive": "1778920788981",
      "sessionCount": 23,
      "rank": 12
    },
    {
      "name": "Dhananjay",
      "agentId": "dhananjay_workspace",
      "tokensIn": 2317331,
      "tokensOut": 760496,
      "totalTokens": 3077827,
      "weeklyTokensIn": 583323,
      "weeklyTokensOut": 191434,
      "weeklyTokens": 774757,
      "estimatedHours": 5.4,
      "weeklyHours": 1.4,
      "totalCost": 6.8343,
      "weeklyCost": 1.7203,
      "adminCost": 0.0,
      "weeklyAdminCost": 0.0,
      "employeeCost": 6.8343,
      "weeklyEmployeeCost": 1.7203,
      "adminSessionCount": 0,
      "totalRuntimeMs": 60929,
      "weeklyRuntimeMs": 15337,
      "streak": 2,
      "lastActive": "1778682974874",
      "sessionCount": 24,
      "rank": 13
    },
    {
      "name": "Nidhi",
      "agentId": "nidhi_workspace",
      "tokensIn": 1816782,
      "tokensOut": 552220,
      "totalTokens": 2369002,
      "weeklyTokensIn": 709139,
      "weeklyTokensOut": 215546,
      "weeklyTokens": 924685,
      "estimatedHours": 3.7,
      "weeklyHours": 1.4,
      "totalCost": 5.485,
      "weeklyCost": 2.1409,
      "adminCost": 0.0,
      "weeklyAdminCost": 0.0,
      "employeeCost": 5.485,
      "weeklyEmployeeCost": 2.1409,
      "adminSessionCount": 0,
      "totalRuntimeMs": 233847,
      "weeklyRuntimeMs": 91276,
      "streak": 2,
      "lastActive": "1778744937818",
      "sessionCount": 18,
      "rank": 14
    },
    {
      "name": "Akshay",
      "agentId": "akshay_workspace",
      "tokensIn": 1314269,
      "tokensOut": 504060,
      "totalTokens": 1818329,
      "weeklyTokensIn": 374459,
      "weeklyTokensOut": 143616,
      "weeklyTokens": 518075,
      "estimatedHours": 2.7,
      "weeklyHours": 0.8,
      "totalCost": 5.2046,
      "weeklyCost": 1.4829,
      "adminCost": 0.0,
      "weeklyAdminCost": 0.0,
      "employeeCost": 5.2046,
      "weeklyEmployeeCost": 1.4829,
      "adminSessionCount": 0,
      "totalRuntimeMs": 38524,
      "weeklyRuntimeMs": 10976,
      "streak": 1,
      "lastActive": "1778891419678",
      "sessionCount": 14,
      "rank": 15
    },
    {
      "name": "Manju",
      "agentId": "manju_workspace",
      "tokensIn": 1409880,
      "tokensOut": 584516,
      "totalTokens": 1994396,
      "weeklyTokensIn": 379622,
      "weeklyTokensOut": 157386,
      "weeklyTokens": 537008,
      "estimatedHours": 4.2,
      "weeklyHours": 1.1,
      "totalCost": 4.5857,
      "weeklyCost": 1.2347,
      "adminCost": 0.0,
      "weeklyAdminCost": 0.0,
      "employeeCost": 4.5857,
      "weeklyEmployeeCost": 1.2347,
      "adminSessionCount": 0,
      "totalRuntimeMs": 154252,
      "weeklyRuntimeMs": 41533,
      "streak": 1,
      "lastActive": "1778827793389",
      "sessionCount": 18,
      "rank": 16
    },
    {
      "name": "Gopika",
      "agentId": "gopika_workspace",
      "tokensIn": 209418,
      "tokensOut": 69785,
      "totalTokens": 279203,
      "weeklyTokensIn": 79699,
      "weeklyTokensOut": 26559,
      "weeklyTokens": 106258,
      "estimatedHours": 0.6,
      "weeklyHours": 0.2,
      "totalCost": 0.9453,
      "weeklyCost": 0.3598,
      "adminCost": 0.0,
      "weeklyAdminCost": 0.0,
      "employeeCost": 0.9453,
      "weeklyEmployeeCost": 0.3598,
      "adminSessionCount": 0,
      "totalRuntimeMs": 122807,
      "weeklyRuntimeMs": 46737,
      "streak": 0,
      "lastActive": "1778321358349",
      "sessionCount": 1,
      "rank": 17
    },
    {
      "name": "Varsha",
      "agentId": "varsha_workspace",
      "tokensIn": 198877,
      "tokensOut": 62078,
      "totalTokens": 260955,
      "weeklyTokensIn": 65757,
      "weeklyTokensOut": 20526,
      "weeklyTokens": 86283,
      "estimatedHours": 0.5,
      "weeklyHours": 0.2,
      "totalCost": 0.9437,
      "weeklyCost": 0.312,
      "adminCost": 0.0,
      "weeklyAdminCost": 0.0,
      "employeeCost": 0.9437,
      "weeklyEmployeeCost": 0.312,
      "adminSessionCount": 0,
      "totalRuntimeMs": 22367,
      "weeklyRuntimeMs": 7395,
      "streak": 0,
      "lastActive": "1777925594597",
      "sessionCount": 2,
      "rank": 18
    },
    {
      "name": "Rohit",
      "agentId": "rohit_workspace",
      "tokensIn": 212860,
      "tokensOut": 63705,
      "totalTokens": 276565,
      "weeklyTokensIn": 74347,
      "weeklyTokensOut": 22251,
      "weeklyTokens": 96598,
      "estimatedHours": 0.6,
      "weeklyHours": 0.2,
      "totalCost": 0.9164,
      "weeklyCost": 0.3201,
      "adminCost": 0.0,
      "weeklyAdminCost": 0.0,
      "employeeCost": 0.9164,
      "weeklyEmployeeCost": 0.3201,
      "adminSessionCount": 0,
      "totalRuntimeMs": 9894,
      "weeklyRuntimeMs": 3455,
      "streak": 0,
      "lastActive": "1777997176478",
      "sessionCount": 2,
      "rank": 19
    },
    {
      "name": "Arvind",
      "agentId": "arvind_workspace",
      "tokensIn": 192755,
      "tokensOut": 73885,
      "totalTokens": 266640,
      "weeklyTokensIn": 55930,
      "weeklyTokensOut": 21438,
      "weeklyTokens": 77368,
      "estimatedHours": 0.5,
      "weeklyHours": 0.1,
      "totalCost": 0.8101,
      "weeklyCost": 0.2351,
      "adminCost": 0.0,
      "weeklyAdminCost": 0.0,
      "employeeCost": 0.8101,
      "weeklyEmployeeCost": 0.2351,
      "adminSessionCount": 0,
      "totalRuntimeMs": 24286,
      "weeklyRuntimeMs": 7046,
      "streak": 0,
      "lastActive": "1778398125617",
      "sessionCount": 1,
      "rank": 20
    },
    {
      "name": "Will",
      "agentId": "will_workspace",
      "tokensIn": 174631,
      "tokensOut": 74564,
      "totalTokens": 249195,
      "weeklyTokensIn": 61034,
      "weeklyTokensOut": 26061,
      "weeklyTokens": 87095,
      "estimatedHours": 0.5,
      "weeklyHours": 0.2,
      "totalCost": 0.7959,
      "weeklyCost": 0.2782,
      "adminCost": 0.0,
      "weeklyAdminCost": 0.0,
      "employeeCost": 0.7959,
      "weeklyEmployeeCost": 0.2782,
      "adminSessionCount": 0,
      "totalRuntimeMs": 32073,
      "weeklyRuntimeMs": 11209,
      "streak": 0,
      "lastActive": "1778443896015",
      "sessionCount": 1,
      "rank": 21
    },
    {
      "name": "Akash",
      "agentId": "akash_workspace",
      "tokensIn": 169797,
      "tokensOut": 55039,
      "totalTokens": 224836,
      "weeklyTokensIn": 64396,
      "weeklyTokensOut": 20874,
      "weeklyTokens": 85270,
      "estimatedHours": 0.5,
      "weeklyHours": 0.2,
      "totalCost": 0.7567,
      "weeklyCost": 0.287,
      "adminCost": 0.0,
      "weeklyAdminCost": 0.0,
      "employeeCost": 0.7567,
      "weeklyEmployeeCost": 0.287,
      "adminSessionCount": 0,
      "totalRuntimeMs": 17624,
      "weeklyRuntimeMs": 6684,
      "streak": 0,
      "lastActive": "1777829408537",
      "sessionCount": 1,
      "rank": 22
    },
    {
      "name": "Naveen",
      "agentId": "naveen_workspace",
      "tokensIn": 195958,
      "tokensOut": 69806,
      "totalTokens": 265764,
      "weeklyTokensIn": 56276,
      "weeklyTokensOut": 20047,
      "weeklyTokens": 76323,
      "estimatedHours": 0.5,
      "weeklyHours": 0.1,
      "totalCost": 0.7553,
      "weeklyCost": 0.2169,
      "adminCost": 0.0,
      "weeklyAdminCost": 0.0,
      "employeeCost": 0.7553,
      "weeklyEmployeeCost": 0.2169,
      "adminSessionCount": 0,
      "totalRuntimeMs": 32791,
      "weeklyRuntimeMs": 9417,
      "streak": 0,
      "lastActive": "1778540177076",
      "sessionCount": 2,
      "rank": 23
    },
    {
      "name": "Sagarkarpe",
      "agentId": "sagarkarpe_workspace",
      "tokensIn": 157295,
      "tokensOut": 65601,
      "totalTokens": 222896,
      "weeklyTokensIn": 40940,
      "weeklyTokensOut": 17074,
      "weeklyTokens": 58014,
      "estimatedHours": 0.5,
      "weeklyHours": 0.1,
      "totalCost": 0.7203,
      "weeklyCost": 0.1875,
      "adminCost": 0.0,
      "weeklyAdminCost": 0.0,
      "employeeCost": 0.7203,
      "weeklyEmployeeCost": 0.1875,
      "adminSessionCount": 0,
      "totalRuntimeMs": 24609,
      "weeklyRuntimeMs": 6405,
      "streak": 0,
      "lastActive": "1778526368532",
      "sessionCount": 1,
      "rank": 24
    },
    {
      "name": "Nidhin",
      "agentId": "nidhin_workspace",
      "tokensIn": 168604,
      "tokensOut": 65881,
      "totalTokens": 234485,
      "weeklyTokensIn": 52863,
      "weeklyTokensOut": 20656,
      "weeklyTokens": 73519,
      "estimatedHours": 0.4,
      "weeklyHours": 0.1,
      "totalCost": 0.7004,
      "weeklyCost": 0.2196,
      "adminCost": 0.0,
      "weeklyAdminCost": 0.0,
      "employeeCost": 0.7004,
      "weeklyEmployeeCost": 0.2196,
      "adminSessionCount": 0,
      "totalRuntimeMs": 8505,
      "weeklyRuntimeMs": 2666,
      "streak": 0,
      "lastActive": "1777983670733",
      "sessionCount": 1,
      "rank": 25
    },
    {
      "name": "Shivakumar",
      "agentId": "shivakumar_workspace",
      "tokensIn": 161809,
      "tokensOut": 51691,
      "totalTokens": 213500,
      "weeklyTokensIn": 56407,
      "weeklyTokensOut": 18020,
      "weeklyTokens": 74427,
      "estimatedHours": 0.4,
      "weeklyHours": 0.1,
      "totalCost": 0.6875,
      "weeklyCost": 0.2397,
      "adminCost": 0.0,
      "weeklyAdminCost": 0.0,
      "employeeCost": 0.6875,
      "weeklyEmployeeCost": 0.2397,
      "adminSessionCount": 0,
      "totalRuntimeMs": 13933,
      "weeklyRuntimeMs": 4857,
      "streak": 0,
      "lastActive": "1777873766708",
      "sessionCount": 1,
      "rank": 26
    },
    {
      "name": "Apurva",
      "agentId": "apurva_workspace",
      "tokensIn": 180825,
      "tokensOut": 71604,
      "totalTokens": 252429,
      "weeklyTokensIn": 62565,
      "weeklyTokensOut": 24775,
      "weeklyTokens": 87340,
      "estimatedHours": 0.5,
      "weeklyHours": 0.2,
      "totalCost": 0.6765,
      "weeklyCost": 0.2341,
      "adminCost": 0.0,
      "weeklyAdminCost": 0.0,
      "employeeCost": 0.6765,
      "weeklyEmployeeCost": 0.2341,
      "adminSessionCount": 0,
      "totalRuntimeMs": 7510,
      "weeklyRuntimeMs": 2598,
      "streak": 0,
      "lastActive": "1777919476249",
      "sessionCount": 1,
      "rank": 27
    },
    {
      "name": "Pawan",
      "agentId": "pawan_workspace",
      "tokensIn": 169636,
      "tokensOut": 65213,
      "totalTokens": 234849,
      "weeklyTokensIn": 65110,
      "weeklyTokensOut": 25031,
      "weeklyTokens": 90141,
      "estimatedHours": 0.5,
      "weeklyHours": 0.2,
      "totalCost": 0.6677,
      "weeklyCost": 0.2563,
      "adminCost": 0.0,
      "weeklyAdminCost": 0.0,
      "employeeCost": 0.6677,
      "weeklyEmployeeCost": 0.2563,
      "adminSessionCount": 0,
      "totalRuntimeMs": 210178,
      "weeklyRuntimeMs": 80671,
      "streak": 0,
      "lastActive": "1778574054563",
      "sessionCount": 1,
      "rank": 28
    },
    {
      "name": "Communal",
      "agentId": "communal_workspace",
      "tokensIn": 146400,
      "tokensOut": 59518,
      "totalTokens": 205918,
      "weeklyTokensIn": 45870,
      "weeklyTokensOut": 18649,
      "weeklyTokens": 64519,
      "estimatedHours": 0.5,
      "weeklyHours": 0.2,
      "totalCost": 0.6237,
      "weeklyCost": 0.1954,
      "adminCost": 0.0,
      "weeklyAdminCost": 0.0,
      "employeeCost": 0.6237,
      "weeklyEmployeeCost": 0.1954,
      "adminSessionCount": 0,
      "totalRuntimeMs": 6291,
      "weeklyRuntimeMs": 1971,
      "streak": 0,
      "lastActive": "1778546442594",
      "sessionCount": 1,
      "rank": 29
    },
    {
      "name": "Anupam",
      "agentId": "anupam_workspace",
      "tokensIn": 137463,
      "tokensOut": 49050,
      "totalTokens": 186513,
      "weeklyTokensIn": 53679,
      "weeklyTokensOut": 19153,
      "weeklyTokens": 72832,
      "estimatedHours": 0.4,
      "weeklyHours": 0.2,
      "totalCost": 0.5907,
      "weeklyCost": 0.2307,
      "adminCost": 0.0,
      "weeklyAdminCost": 0.0,
      "employeeCost": 0.5907,
      "weeklyEmployeeCost": 0.2307,
      "adminSessionCount": 0,
      "totalRuntimeMs": 11820,
      "weeklyRuntimeMs": 4615,
      "streak": 0,
      "lastActive": "1777726783482",
      "sessionCount": 1,
      "rank": 30
    },
    {
      "name": "Prasad",
      "agentId": "prasad_workspace",
      "tokensIn": 151071,
      "tokensOut": 50214,
      "totalTokens": 201285,
      "weeklyTokensIn": 52494,
      "weeklyTokensOut": 17449,
      "weeklyTokens": 69943,
      "estimatedHours": 0.4,
      "weeklyHours": 0.1,
      "totalCost": 0.5797,
      "weeklyCost": 0.2014,
      "adminCost": 0.0,
      "weeklyAdminCost": 0.0,
      "employeeCost": 0.5797,
      "weeklyEmployeeCost": 0.2014,
      "adminSessionCount": 0,
      "totalRuntimeMs": 215005,
      "weeklyRuntimeMs": 74710,
      "streak": 0,
      "lastActive": "1777946306997",
      "sessionCount": 1,
      "rank": 31
    },
    {
      "name": "Shreyansh",
      "agentId": "shreyansh_workspace",
      "tokensIn": 118914,
      "tokensOut": 48742,
      "totalTokens": 167656,
      "weeklyTokensIn": 40497,
      "weeklyTokensOut": 16599,
      "weeklyTokens": 57096,
      "estimatedHours": 0.4,
      "weeklyHours": 0.1,
      "totalCost": 0.5675,
      "weeklyCost": 0.1933,
      "adminCost": 0.0,
      "weeklyAdminCost": 0.0,
      "employeeCost": 0.5675,
      "weeklyEmployeeCost": 0.1933,
      "adminSessionCount": 0,
      "totalRuntimeMs": 264596,
      "weeklyRuntimeMs": 90110,
      "streak": 0,
      "lastActive": "1778642862963",
      "sessionCount": 1,
      "rank": 32
    },
    {
      "name": "Swapnil",
      "agentId": "swapnil_workspace",
      "tokensIn": 149324,
      "tokensOut": 54833,
      "totalTokens": 204157,
      "weeklyTokensIn": 51789,
      "weeklyTokensOut": 19017,
      "weeklyTokens": 70806,
      "estimatedHours": 0.4,
      "weeklyHours": 0.1,
      "totalCost": 0.564,
      "weeklyCost": 0.1956,
      "adminCost": 0.0,
      "weeklyAdminCost": 0.0,
      "employeeCost": 0.564,
      "weeklyEmployeeCost": 0.1956,
      "adminSessionCount": 0,
      "totalRuntimeMs": 6058,
      "weeklyRuntimeMs": 2101,
      "streak": 0,
      "lastActive": "1778018836584",
      "sessionCount": 1,
      "rank": 33
    },
    {
      "name": "Kristi",
      "agentId": "kristi_workspace",
      "tokensIn": 169918,
      "tokensOut": 45750,
      "totalTokens": 215668,
      "weeklyTokensIn": 43955,
      "weeklyTokensOut": 11835,
      "weeklyTokens": 55790,
      "estimatedHours": 0.4,
      "weeklyHours": 0.1,
      "totalCost": 0.5386,
      "weeklyCost": 0.1393,
      "adminCost": 0.0,
      "weeklyAdminCost": 0.0,
      "employeeCost": 0.5386,
      "weeklyEmployeeCost": 0.1393,
      "adminSessionCount": 0,
      "totalRuntimeMs": 17562,
      "weeklyRuntimeMs": 4543,
      "streak": 0,
      "lastActive": "1777814170592",
      "sessionCount": 1,
      "rank": 34
    },
    {
      "name": "Neel",
      "agentId": "neel_workspace",
      "tokensIn": 109216,
      "tokensOut": 46648,
      "totalTokens": 155864,
      "weeklyTokensIn": 28408,
      "weeklyTokensOut": 12133,
      "weeklyTokens": 40541,
      "estimatedHours": 0.3,
      "weeklyHours": 0.1,
      "totalCost": 0.4644,
      "weeklyCost": 0.1208,
      "adminCost": 0.0,
      "weeklyAdminCost": 0.0,
      "employeeCost": 0.4644,
      "weeklyEmployeeCost": 0.1208,
      "adminSessionCount": 0,
      "totalRuntimeMs": 13487,
      "weeklyRuntimeMs": 3508,
      "streak": 0,
      "lastActive": "1778625549361",
      "sessionCount": 1,
      "rank": 35
    }
  ],
  "generatedAt": "2026-05-15T18:07:56.818137+05:30",
  "weekStart": "2026-05-11T00:00:00+05:30",
  "summary": {
    "totalEmployees": 35,
    "totalWeeklyHours": 66.1,
    "avgWeeklyHours": 1.9,
    "goalMetCount": 6,
    "totalTokens": 117951248,
    "totalWeeklyTokens": 38567749,
    "totalCost": 287.46,
    "weeklyCost": 93.83,
    "adminCost": 0.0,
    "weeklyAdminCost": 0.0,
    "employeeCost": 287.46,
    "weeklyEmployeeCost": 93.83,
    "adminNote": "Admin costs include sub-agent operations, dashboard builds, PDF generation \u2014 not recurring employee usage"
  }
}